litrevai/__about__.py
litrevai/__init__.py
litrevai/acm.py
litrevai/extract.py
litrevai/literature_review.py
litrevai/pdf2text.py
litrevai/project.py
litrevai/prompt.py
litrevai/query.py
litrevai/topic_modelling.py
litrevai/translate.py
litrevai/types.py
litrevai/util.py
litrevai/zotero_connector.py
litrevai/data/prompts/criteria.txt
litrevai/data/prompts/likert.txt
litrevai/data/prompts/list.txt
litrevai/data/prompts/list_extraction
litrevai/data/prompts/open.txt
litrevai/data/prompts/options.txt
litrevai/data/prompts/yes_no.txt
litrevai/llm/__init__.py
litrevai/llm/base.py
litrevai/llm/custom_endpoint.py
litrevai/llm/huggingface_endpoint.py
litrevai/llm/openai_endpoint.py
litrevai/model/__init__.py
litrevai/model/database.py
litrevai/model/models.py
litrevai/model/vector_store.py
litrevai-0.0.4.dist-info/METADATA
litrevai-0.0.4.dist-info/WHEEL
litrevai-0.0.4.dist-info/licenses/LICENSE.txt
litrevai-0.0.4.dist-info/RECORD
