Metadata-Version: 2.3
Name: litrevai
Version: 0.0.4
Summary: LitRevAI (Literature Review AI) is a Python package designed to automate systematic literature reviews using natural language processing (NLP) techniques.
Project-URL: Documentation, https://github.com/soespa/litrevai#readme
Project-URL: Issues, https://github.com/soespa/litrevai/issues
Project-URL: Source, https://github.com/soespa/litrevai
Author-email: Soeren Sparmann <soeren.sparmann@uni-paderborn.de>
License: MIT
Classifier: Development Status :: 4 - Beta
Classifier: Programming Language :: Python
Classifier: Programming Language :: Python :: 3.9
Classifier: Programming Language :: Python :: 3.10
Classifier: Programming Language :: Python :: 3.11
Classifier: Programming Language :: Python :: 3.12
Classifier: Programming Language :: Python :: Implementation :: CPython
Classifier: Programming Language :: Python :: Implementation :: PyPy
Requires-Python: >=3.9
Requires-Dist: bertopic
Requires-Dist: bibtexparser==2.0.0b7
Requires-Dist: huggingface-hub
Requires-Dist: lancedb
Requires-Dist: langchain-text-splitters
Requires-Dist: nltk
Requires-Dist: openai
Requires-Dist: openpyxl
Requires-Dist: pandas
Requires-Dist: pdfminer-six
Requires-Dist: plotly
Requires-Dist: pyarrow
Requires-Dist: python-dotenv
Requires-Dist: requests
Requires-Dist: sqlalchemy
Requires-Dist: tqdm
